LICENSE
MANIFEST.in
README.md
setup.py
bin/viaconstructor
viaconstructor/__init__.py
viaconstructor/__main__.py
viaconstructor/calc.py
viaconstructor/draw2d.py
viaconstructor/dxfcolors.py
viaconstructor/gldraw.py
viaconstructor/input_plugins_base.py
viaconstructor/machine_cmd.py
viaconstructor/setupdefaults.py
viaconstructor/vc_types.py
viaconstructor/viaconstructor.py
viaconstructor.egg-info/PKG-INFO
viaconstructor.egg-info/SOURCES.txt
viaconstructor.egg-info/dependency_links.txt
viaconstructor.egg-info/requires.txt
viaconstructor.egg-info/top_level.txt
viaconstructor/ext/HersheyFonts/HersheyFonts.py
viaconstructor/ext/HersheyFonts/__init__.py
viaconstructor/ext/HersheyFonts/__main__.py
viaconstructor/ext/cavaliercontours/__init__.py
viaconstructor/ext/cavaliercontours/cavaliercontours.py
viaconstructor/ext/cavaliercontours/lib/libCavalierContours.aarch64-linux.so
viaconstructor/ext/cavaliercontours/lib/libCavalierContours.x86_64-darwin.so
viaconstructor/ext/cavaliercontours/lib/libCavalierContours.x86_64-linux.so
viaconstructor/ext/meshcut/meshcut.py
viaconstructor/ext/stl/__about__.py
viaconstructor/ext/stl/__init__.py
viaconstructor/ext/stl/base.py
viaconstructor/ext/stl/main.py
viaconstructor/ext/stl/mesh.py
viaconstructor/ext/stl/stl.py
viaconstructor/ext/stl/utils.py
viaconstructor/ext/svgpathtools/__init__.py
viaconstructor/ext/svgpathtools/bezier.py
viaconstructor/ext/svgpathtools/document.py
viaconstructor/ext/svgpathtools/misctools.py
viaconstructor/ext/svgpathtools/parser.py
viaconstructor/ext/svgpathtools/path.py
viaconstructor/ext/svgpathtools/paths2svg.py
viaconstructor/ext/svgpathtools/polytools.py
viaconstructor/ext/svgpathtools/smoothing.py
viaconstructor/ext/svgpathtools/svg_io_sax.py
viaconstructor/ext/svgpathtools/svg_to_paths.py
viaconstructor/icons/append.png
viaconstructor/icons/box.png
viaconstructor/icons/camotics.png
viaconstructor/icons/delete.png
viaconstructor/icons/exit.png
viaconstructor/icons/flip-x.png
viaconstructor/icons/flip-y.png
viaconstructor/icons/fonts.png
viaconstructor/icons/gears.png
viaconstructor/icons/load-setup-gcode.png
viaconstructor/icons/load-setup.png
viaconstructor/icons/load-tooltable.png
