Metadata-Version: 2.1
Name: viaconstructor
Version: 0.7.0
Summary: python based cam-tool to convert dxf into gcode
Home-page: https://github.com/multigcs/viaconstructor
Author: Oliver Dippel
Author-email: o.dippel@gmx.de
License: LICENSE
License-File: LICENSE
